lib/__init__.py
lib/lakshya (2).py
lib/lakshya.py
Topsis_lakshya_102103453-0.0.1.dist-info/METADATA
Topsis_lakshya_102103453-0.0.1.dist-info/WHEEL
Topsis_lakshya_102103453-0.0.1.dist-info/top_level.txt
Topsis_lakshya_102103453-0.0.1.dist-info/RECORD
